django_o18n-1.0.dist-info/DESCRIPTION.rst
django_o18n-1.0.dist-info/METADATA
django_o18n-1.0.dist-info/metadata.json
django_o18n-1.0.dist-info/RECORD
django_o18n-1.0.dist-info/top_level.txt
django_o18n-1.0.dist-info/WHEEL
o18n/__init__.py
o18n/country.py
o18n/middleware.py
o18n/monkey.py
o18n/test_country.py
o18n/test_o18n.py
o18n/test_settings.py
o18n/test_urls.py
o18n/test_views.py
o18n/urls.py
o18n/util.py
