Metadata-Version: 2.0
Name: django-o18n
Version: 1.0
Summary: /<country>/<language>/ URL scheme, like Django's i18n_patterns.
Home-page: https://github.com/oscaro/django-o18n
Author: Aymeric Augustin
Author-email: aymeric.augustin@oscaro.com
License: BSD
Platform: UNKNOWN
Classifier: Development Status :: 5 - Production/Stable
Classifier: Environment :: Web Environment
Classifier: Framework :: Django
Classifier: Intended Audience :: Developers
Classifier: License :: OSI Approved :: BSD License
Classifier: Operating System :: OS Independent
Classifier: Programming Language :: Python
Classifier: Programming Language :: Python :: 2
Classifier: Programming Language :: Python :: 2.7
Classifier: Programming Language :: Python :: 3
Classifier: Programming Language :: Python :: 3.2
Classifier: Programming Language :: Python :: 3.3
Classifier: Programming Language :: Python :: 3.4
